Workbook

Sheet Start here
A1: The 6 Pass · partner pipeline
A2: 441 places to approach, researched October 2026 from public sources. Counts below update by themselves.
A4: How to use it
A5: 1. Work one neighbourhood at a time. Wave 1 is the six launch neighbourhoods; start with Ossington.
A6: 2. Before walking in, check the place is still open (Open? column). Some rows note weak online evidence.
A7: 3. Every row you touch gets a Status, a Next step and a Next step date. Overdue dates turn red.
A8: 4. Write their slow nights and offer idea as you hear them. That becomes their offer in the app.
A9: 5. Be picky: we need 50 Founding Partners, not 300. A 'Not now' with a reason is a good outcome.
A10: Contacts are blank on purpose: ask for the owner or general manager in person, then fill them in.
A13: By status
A14: Target | B14: =COUNTIF(Pipeline!N:N,"Target")
A15: Contacted | B15: =COUNTIF(Pipeline!N:N,"Contacted")
A16: Meeting booked | B16: =COUNTIF(Pipeline!N:N,"Meeting booked")
A17: Met | B17: =COUNTIF(Pipeline!N:N,"Met")
A18: LOI signed | B18: =COUNTIF(Pipeline!N:N,"LOI signed")
A19: Agreement signed | B19: =COUNTIF(Pipeline!N:N,"Agreement signed")
A20: Not now | B20: =COUNTIF(Pipeline!N:N,"Not now")
A21: Goal for the first week: 10 conversations, 5 demos, 2 letters of intent.
A23: Neighbourhood | B23: Places | C23: Contacted+ | D23: Met | E23: LOI signed | F23: Signed
A24: Ossington (wave 1) | B24: =COUNTIF(Pipeline!D:D,"Ossington") | C24: =COUNTIFS(Pipeline!D:D,"Ossington",Pipeline!N:N,"<>Target",Pipeline!N:N,"<>") | D24: =COUNTIFS(Pipeline!D:D,"Ossington",Pipeline!N:N,"Met") | E24: =COUNTIFS(Pipeline!D:D,"Ossington",Pipeline!N:N,"LOI signed") | F24: =COUNTIFS(Pipeline!D:D,"Ossington",Pipeline!N:N,"Agreement signed")
A25: Queen West (wave 1) | B25: =COUNTIF(Pipeline!D:D,"Queen West") | C25: =COUNTIFS(Pipeline!D:D,"Queen West",Pipeline!N:N,"<>Target",Pipeline!N:N,"<>") | D25: =COUNTIFS(Pipeline!D:D,"Queen West",Pipeline!N:N,"Met") | E25: =COUNTIFS(Pipeline!D:D,"Queen West",Pipeline!N:N,"LOI signed") | F25: =COUNTIFS(Pipeline!D:D,"Queen West",Pipeline!N:N,"Agreement signed")
A26: King West (wave 1) | B26: =COUNTIF(Pipeline!D:D,"King West") | C26: =COUNTIFS(Pipeline!D:D,"King West",Pipeline!N:N,"<>Target",Pipeline!N:N,"<>") | D26: =COUNTIFS(Pipeline!D:D,"King West",Pipeline!N:N,"Met") | E26: =COUNTIFS(Pipeline!D:D,"King West",Pipeline!N:N,"LOI signed") | F26: =COUNTIFS(Pipeline!D:D,"King West",Pipeline!N:N,"Agreement signed")
A27: Financial District (wave 1) | B27: =COUNTIF(Pipeline!D:D,"Financial District") | C27: =COUNTIFS(Pipeline!D:D,"Financial District",Pipeline!N:N,"<>Target",Pipeline!N:N,"<>") | D27: =COUNTIFS(Pipeline!D:D,"Financial District",Pipeline!N:N,"Met") | E27: =COUNTIFS(Pipeline!D:D,"Financial District",Pipeline!N:N,"LOI signed") | F27: =COUNTIFS(Pipeline!D:D,"Financial District",Pipeline!N:N,"Agreement signed")
A28: Yorkville (wave 1) | B28: =COUNTIF(Pipeline!D:D,"Yorkville") | C28: =COUNTIFS(Pipeline!D:D,"Yorkville",Pipeline!N:N,"<>Target",Pipeline!N:N,"<>") | D28: =COUNTIFS(Pipeline!D:D,"Yorkville",Pipeline!N:N,"Met") | E28: =COUNTIFS(Pipeline!D:D,"Yorkville",Pipeline!N:N,"LOI signed") | F28: =COUNTIFS(Pipeline!D:D,"Yorkville",Pipeline!N:N,"Agreement signed")
A29: Leslieville (wave 1) | B29: =COUNTIF(Pipeline!D:D,"Leslieville") | C29: =COUNTIFS(Pipeline!D:D,"Leslieville",Pipeline!N:N,"<>Target",Pipeline!N:N,"<>") | D29: =COUNTIFS(Pipeline!D:D,"Leslieville",Pipeline!N:N,"Met") | E29: =COUNTIFS(Pipeline!D:D,"Leslieville",Pipeline!N:N,"LOI signed") | F29: =COUNTIFS(Pipeline!D:D,"Leslieville",Pipeline!N:N,"Agreement signed")
A30: Little Italy | B30: =COUNTIF(Pipeline!D:D,"Little Italy") | C30: =COUNTIFS(Pipeline!D:D,"Little Italy",Pipeline!N:N,"<>Target",Pipeline!N:N,"<>") | D30: =COUNTIFS(Pipeline!D:D,"Little Italy",Pipeline!N:N,"Met") | E30: =COUNTIFS(Pipeline!D:D,"Little Italy",Pipeline!N:N,"LOI signed") | F30: =COUNTIFS(Pipeline!D:D,"Little Italy",Pipeline!N:N,"Agreement signed")
A31: Kensington and Chinatown | B31: =COUNTIF(Pipeline!D:D,"Kensington and Chinatown") | C31: =COUNTIFS(Pipeline!D:D,"Kensington and Chinatown",Pipeline!N:N,"<>Target",Pipeline!N:N,"<>") | D31: =COUNTIFS(Pipeline!D:D,"Kensington and Chinatown",Pipeline!N:N,"Met") | E31: =COUNTIFS(Pipeline!D:D,"Kensington and Chinatown",Pipeline!N:N,"LOI signed") | F31: =COUNTIFS(Pipeline!D:D,"Kensington and Chinatown",Pipeline!N:N,"Agreement signed")
A32: The Annex | B32: =COUNTIF(Pipeline!D:D,"The Annex") | C32: =COUNTIFS(Pipeline!D:D,"The Annex",Pipeline!N:N,"<>Target",Pipeline!N:N,"<>") | D32: =COUNTIFS(Pipeline!D:D,"The Annex",Pipeline!N:N,"Met") | E32: =COUNTIFS(Pipeline!D:D,"The Annex",Pipeline!N:N,"LOI signed") | F32: =COUNTIFS(Pipeline!D:D,"The Annex",Pipeline!N:N,"Agreement signed")
A33: Roncesvalles | B33: =COUNTIF(Pipeline!D:D,"Roncesvalles") | C33: =COUNTIFS(Pipeline!D:D,"Roncesvalles",Pipeline!N:N,"<>Target",Pipeline!N:N,"<>") | D33: =COUNTIFS(Pipeline!D:D,"Roncesvalles",Pipeline!N:N,"Met") | E33: =COUNTIFS(Pipeline!D:D,"Roncesvalles",Pipeline!N:N,"LOI signed") | F33: =COUNTIFS(Pipeline!D:D,"Roncesvalles",Pipeline!N:N,"Agreement signed")
A34: Danforth | B34: =COUNTIF(Pipeline!D:D,"Danforth") | C34: =COUNTIFS(Pipeline!D:D,"Danforth",Pipeline!N:N,"<>Target",Pipeline!N:N,"<>") | D34: =COUNTIFS(Pipeline!D:D,"Danforth",Pipeline!N:N,"Met") | E34: =COUNTIFS(Pipeline!D:D,"Danforth",Pipeline!N:N,"LOI signed") | F34: =COUNTIFS(Pipeline!D:D,"Danforth",Pipeline!N:N,"Agreement signed")
A35: Liberty Village | B35: =COUNTIF(Pipeline!D:D,"Liberty Village") | C35: =COUNTIFS(Pipeline!D:D,"Liberty Village",Pipeline!N:N,"<>Target",Pipeline!N:N,"<>") | D35: =COUNTIFS(Pipeline!D:D,"Liberty Village",Pipeline!N:N,"Met") | E35: =COUNTIFS(Pipeline!D:D,"Liberty Village",Pipeline!N:N,"LOI signed") | F35: =COUNTIFS(Pipeline!D:D,"Liberty Village",Pipeline!N:N,"Agreement signed")
A36: Little Portugal | B36: =COUNTIF(Pipeline!D:D,"Little Portugal") | C36: =COUNTIFS(Pipeline!D:D,"Little Portugal",Pipeline!N:N,"<>Target",Pipeline!N:N,"<>") | D36: =COUNTIFS(Pipeline!D:D,"Little Portugal",Pipeline!N:N,"Met") | E36: =COUNTIFS(Pipeline!D:D,"Little Portugal",Pipeline!N:N,"LOI signed") | F36: =COUNTIFS(Pipeline!D:D,"Little Portugal",Pipeline!N:N,"Agreement signed")
A37: Parkdale | B37: =COUNTIF(Pipeline!D:D,"Parkdale") | C37: =COUNTIFS(Pipeline!D:D,"Parkdale",Pipeline!N:N,"<>Target",Pipeline!N:N,"<>") | D37: =COUNTIFS(Pipeline!D:D,"Parkdale",Pipeline!N:N,"Met") | E37: =COUNTIFS(Pipeline!D:D,"Parkdale",Pipeline!N:N,"LOI signed") | F37: =COUNTIFS(Pipeline!D:D,"Parkdale",Pipeline!N:N,"Agreement signed")
A38: The Junction | B38: =COUNTIF(Pipeline!D:D,"The Junction") | C38: =COUNTIFS(Pipeline!D:D,"The Junction",Pipeline!N:N,"<>Target",Pipeline!N:N,"<>") | D38: =COUNTIFS(Pipeline!D:D,"The Junction",Pipeline!N:N,"Met") | E38: =COUNTIFS(Pipeline!D:D,"The Junction",Pipeline!N:N,"LOI signed") | F38: =COUNTIFS(Pipeline!D:D,"The Junction",Pipeline!N:N,"Agreement signed")
A39: St. Clair West | B39: =COUNTIF(Pipeline!D:D,"St. Clair West") | C39: =COUNTIFS(Pipeline!D:D,"St. Clair West",Pipeline!N:N,"<>Target",Pipeline!N:N,"<>") | D39: =COUNTIFS(Pipeline!D:D,"St. Clair West",Pipeline!N:N,"Met") | E39: =COUNTIFS(Pipeline!D:D,"St. Clair West",Pipeline!N:N,"LOI signed") | F39: =COUNTIFS(Pipeline!D:D,"St. Clair West",Pipeline!N:N,"Agreement signed")
A40: Distillery and Corktown | B40: =COUNTIF(Pipeline!D:D,"Distillery and Corktown") | C40: =COUNTIFS(Pipeline!D:D,"Distillery and Corktown",Pipeline!N:N,"<>Target",Pipeline!N:N,"<>") | D40: =COUNTIFS(Pipeline!D:D,"Distillery and Corktown",Pipeline!N:N,"Met") | E40: =COUNTIFS(Pipeline!D:D,"Distillery and Corktown",Pipeline!N:N,"LOI signed") | F40: =COUNTIFS(Pipeline!D:D,"Distillery and Corktown",Pipeline!N:N,"Agreement signed")
A41: Summerhill and Rosedale | B41: =COUNTIF(Pipeline!D:D,"Summerhill and Rosedale") | C41: =COUNTIFS(Pipeline!D:D,"Summerhill and Rosedale",Pipeline!N:N,"<>Target",Pipeline!N:N,"<>") | D41: =COUNTIFS(Pipeline!D:D,"Summerhill and Rosedale",Pipeline!N:N,"Met") | E41: =COUNTIFS(Pipeline!D:D,"Summerhill and Rosedale",Pipeline!N:N,"LOI signed") | F41: =COUNTIFS(Pipeline!D:D,"Summerhill and Rosedale",Pipeline!N:N,"Agreement signed")
A42: Midtown | B42: =COUNTIF(Pipeline!D:D,"Midtown") | C42: =COUNTIFS(Pipeline!D:D,"Midtown",Pipeline!N:N,"<>Target",Pipeline!N:N,"<>") | D42: =COUNTIFS(Pipeline!D:D,"Midtown",Pipeline!N:N,"Met") | E42: =COUNTIFS(Pipeline!D:D,"Midtown",Pipeline!N:N,"LOI signed") | F42: =COUNTIFS(Pipeline!D:D,"Midtown",Pipeline!N:N,"Agreement signed")
A43: Leaside | B43: =COUNTIF(Pipeline!D:D,"Leaside") | C43: =COUNTIFS(Pipeline!D:D,"Leaside",Pipeline!N:N,"<>Target",Pipeline!N:N,"<>") | D43: =COUNTIFS(Pipeline!D:D,"Leaside",Pipeline!N:N,"Met") | E43: =COUNTIFS(Pipeline!D:D,"Leaside",Pipeline!N:N,"LOI signed") | F43: =COUNTIFS(Pipeline!D:D,"Leaside",Pipeline!N:N,"Agreement signed")
A44: Riverdale | B44: =COUNTIF(Pipeline!D:D,"Riverdale") | C44: =COUNTIFS(Pipeline!D:D,"Riverdale",Pipeline!N:N,"<>Target",Pipeline!N:N,"<>") | D44: =COUNTIFS(Pipeline!D:D,"Riverdale",Pipeline!N:N,"Met") | E44: =COUNTIFS(Pipeline!D:D,"Riverdale",Pipeline!N:N,"LOI signed") | F44: =COUNTIFS(Pipeline!D:D,"Riverdale",Pipeline!N:N,"Agreement signed")
A45: Total | B45: =SUM(B24:B44) | C45: =SUM(C24:C44) | D45: =SUM(D24:D44) | E45: =SUM(E24:E44) | F45: =SUM(F24:F44)
A47: By category
A48: Restaurant | B48: =COUNTIF(Pipeline!E:E,"Restaurant")
A49: Brunch | B49: =COUNTIF(Pipeline!E:E,"Brunch")
A50: Café | B50: =COUNTIF(Pipeline!E:E,"Café")
A51: Bakery | B51: =COUNTIF(Pipeline!E:E,"Bakery")
A52: Spa | B52: =COUNTIF(Pipeline!E:E,"Spa")
A53: Studio | B53: =COUNTIF(Pipeline!E:E,"Studio")
A54: Hotel restaurant or spa | B54: =COUNTIF(Pipeline!E:E,"Hotel restaurant or spa")

Sheet Pipeline
A1: # | B1: Wave | C1: Place | D1: Neighbourhood | E1: Category | F1: Cuisine or type | G1: Address | H1: Website | I1: Instagram | J1: Phone | K1: Price | L1: Why it fits | M1: Open? | N1: Status | O1: Contact name | P1: Role | Q1: Contact email or phone | R1: How we know them | S1: Last contact | T1: Next step | U1: Next step date | V1: Slow nights | W1: Offer idea | X1: Notes | Y1: Source
A2: 1 | B2: 1 | C2: Actinolite | D2: Ossington | E2: Restaurant | F2: Contemporary Canadian tasting menu | G2: 971 Ossington Ave | H2: https://www.actinoliterestaurant.com | I2: @actinoliterestaurant | J2: 416-962-8943 | K2: $$$$ | L2: Seasonal tasting-menu room north of the strip, suits an upgrade-style offer. | M2: Not checked | N2: Target | Y2: https://guide.michelin.com/ca/en/ontario/toronto/restaurant/actinolite
A3: 2 | B3: 1 | C3: Antler | D3: Ossington | E3: Restaurant | F3: Wild and foraged Canadian | G3: 1454 Dundas St W | H3: https://www.antlerkitchenbar.com | I3: @antlerkitchenbar | J3: 647-345-8300 | K3: $$$ | L3: Game and foraged menu, a bit further west on Dundas. | M3: Not checked | N3: Target | Y3: https://guide.michelin.com/ca/en/ontario/toronto/restaurant/antler
A4: 3 | B4: 1 | C4: Azhar Kitchen & Bar | D4: Ossington | E4: Restaurant | F4: Middle Eastern | G4: 96 Ossington Ave | H4: https://azhartoronto.com | I4: @azhartoronto | L4: Wood-fired Middle Eastern plates, easy for two. | M4: Not checked | N4: Target | X4: Check it's open before visiting: weak online evidence. | Y4: https://azhartoronto.com
A5: 4 | B5: 1 | C5: Côte de Boeuf | D5: Ossington | E5: Restaurant | F5: French bistro and butcher | G5: 130 Ossington Ave | H5: https://cotedeboeuf.ca | I5: @cotedeboeufossington | L5: Walk-in steak frites bistro, a well-known name on the strip. | M5: Not checked | N5: Target | X5: Check it's open before visiting: weak online evidence. | Y5: https://cotedeboeuf.ca
A6: 5 | B6: 1 | C6: Enoteca Sociale | D6: Ossington | E6: Restaurant | F6: Roman Italian | G6: 1288 Dundas St W | H6: https://sociale.ca | J6: 416-534-1200 | K6: $$ | L6: Bib Gourmand pasta spot on Dundas West. | M6: Not checked | N6: Target | Y6: https://guide.michelin.com/ca/en/ontario/toronto/restaurant/enoteca-sociale
A7: 6 | B7: 1 | C7: Fallen Feather | D7: Ossington | E7: Restaurant | F7: Modern Asian with French technique | I7: @fallenfeather217 | L7: Stylish Asian-French dinner room on the strip. | M7: Not checked | N7: Target | Y7: https://streetsoftoronto.com/food/5-spots-on-ossington-every-foodie-needs-to-try/
A8: 7 | B8: 1 | C8: Fat Choi | D8: Ossington | E8: Restaurant | F8: Plant-based Malaysian and Nyonya | G8: 94 Ossington Ave | H8: https://www.fatchoito.com | J8: 416-901-7667 | L8: Vegan tasting menus, a different option for the list. | M8: Not checked | N8: Target | X8: Check it's open before visiting: weak online evidence. | Y8: https://www.fatchoito.com
A9: 8 | B9: 1 | C9: Favorites Thai | D9: Ossington | E9: Restaurant | F9: Thai, charcoal BBQ | G9: 141 Ossington Ave | H9: https://www.myfavethai.com | I9: @myfavethai | J9: 647-867-3283 | K9: $$ | L9: Bib Gourmand Thai BBQ, a strong value story for members. | M9: Not checked | N9: Target | Y9: https://guide.michelin.com/ca/en/ontario/toronto/restaurant/favorites-thai
A10: 9 | B10: 1 | C10: Gia | D10: Ossington | E10: Restaurant | F10: Plant-forward Italian | G10: 1214 Dundas St W | H10: https://giarestaurant.ca | I10: @giatoronto | J10: 416-535-8888 | K10: $$$ | L10: Plant-forward Italian with Michelin recognition. | M10: Not checked | N10: Target | Y10: https://guide.michelin.com/ca/en/ontario/toronto/restaurant/gia
A11: 10 | B11: 1 | C11: Imanishi Japanese Kitchen | D11: Ossington | E11: Restaurant | F11: Japanese home-style | G11: 1330 Dundas St W | H11: https://www.imanishi.ca | I11: @imanishijapanesekitchen | J11: 416-706-4225 | L11: Tokyo home-style plates in a calm room on Dundas West. | M11: Not checked | N11: Target | Y11: https://streetsoftoronto.com/food/5-restaurants-on-dundas-west-that-every-foodie-needs-to-try/
A12: 11 | B12: 1 | C12: La Banane | D12: Ossington | E12: Restaurant | F12: French, raw bar | G12: 227 Ossington Ave | H12: https://www.labanane.ca | I12: @labananeresto | J12: 416-551-6263 | K12: $$$$ | L12: Michelin-listed French room with a raw bar, good for a special night out. | M12: Not checked | N12: Target | Y12: https://guide.michelin.com/ca/en/ontario/toronto/restaurant/la-banane
A13: 12 | B13: 1 | C13: Linny's | D13: Ossington | E13: Restaurant | F13: Steakhouse, deli | G13: 176 Ossington Ave | H13: https://linnysrestaurant.com | I13: @linnysrestaurant | J13: 647-390-1836 | K13: $$$$ | L13: Premium deli-steakhouse that would be a headline name on the list. | M13: Not checked | N13: Target | Y13: https://guide.michelin.com/ca/en/ontario/toronto/restaurant/linny-s
A14: 13 | B14: 1 | C14: Mamakas Taverna | D14: Ossington | E14: Restaurant | F14: Greek | G14: 80 Ossington Ave | H14: https://mamakas.ca/locations/mamakas-ossington/ | I14: @mamakastaverna | J14: 416-519-5996 | L14: Polished Greek taverna built around sharing plates. | M14: Not checked | N14: Target | Y14: https://mamakas.ca/locations/mamakas-ossington/
A15: 14 | B15: 1 | C15: MSSM Ossington | D15: Ossington | E15: Restaurant | F15: Japanese omakase | G15: 1221 Dundas St W | H15: https://mssmossington.ca | I15: @mssmossington | L15: Edomae omakase counter, a premium sushi option. | M15: Not checked | N15: Target | X15: Check it's open before visiting: weak online evidence. | Y15: https://mssmossington.ca
A16: 15 | B16: 1 | C16: OddSeoul | D16: Ossington | E16: Restaurant | F16: Korean small plates | G16: 90 Ossington Ave | H16: https://oddseoul.ca | I16: @90oddseoul | L16: Late-night Korean small plates, good for a casual date. | M16: Not checked | N16: Target | Y16: https://streetsoftoronto.com/food/5-spots-on-ossington-every-foodie-needs-to-try/
A17: 16 | B17: 1 | C17: Papi & Rosita | D17: Ossington | E17: Restaurant | F17: Comfort food, tacos, pizza, pasta | G17: 198 Ossington Ave | H17: https://www.papiandrosita.com | J17: 416-519-1109 | L17: Newer sister to Papi Chulo's, still building regulars. | M17: Not checked | N17: Target | X17: Check it's open before visiting: weak online evidence. | Y17: https://www.papiandrosita.com
A18: 17 | B18: 1 | C18: Papi Chulo's | D18: Ossington | E18: Restaurant | F18: Mexican | G18: 121 Ossington Ave | H18: https://www.papichulos.ca | I18: @eatpapichulos | L18: Lively, casual Mexican spot that fits a bring-a-friend offer. | M18: Not checked | N18: Target | X18: Check it's open before visiting: weak online evidence. | Y18: https://www.papichulos.ca
A19: 18 | B19: 1 | C19: Pho Tien Thanh | D19: Ossington | E19: Restaurant | F19: Vietnamese | G19: 57 Ossington Ave | H19: https://photienthanh.com | I19: @photienthanhto | J19: 416-588-6997 | K19: $ | L19: Long-standing pho spot, a budget-friendly anchor. | M19: Not checked | N19: Target | Y19: https://guide.michelin.com/ca/en/ontario/toronto/restaurant/pho-tien-thanh
A20: 19 | B20: 1 | C20: Please & Thank You | D20: Ossington | E20: Restaurant | F20: Global small plates | G20: 108 Ossington Ave | I20: @pandtytoronto | L20: Small plates mostly under $20, from the OddSeoul team. | M20: Not checked | N20: Target | Y20: https://streetsoftoronto.com/food/team-behind-one-of-ossingtons-best-restaurants-just-opened-another-must-visit-spot/
A21: 20 | B21: 1 | C21: Taberna LX | D21: Ossington | E21: Restaurant | F21: Portuguese | G21: 1161 Dundas St W | H21: https://tabernalx.com | I21: @taberna_lx_to | J21: 416-516-6660 | L21: Newer Portuguese room near Ossington and Dundas. | M21: Not checked | N21: Target | Y21: https://foodism.ca/eat-drink/bars-restaurants/best-new-restaurants-toronto-fall-2025/
A22: 21 | B22: 1 | C22: The Haifa Room | D22: Ossington | E22: Restaurant | F22: Israeli, Middle Eastern | G22: 224 Ossington Ave | H22: https://www.thehaifaroom.com | L22: Shareable Israeli plates at Ossington and Dundas, easy to bring a friend. | M22: Not checked | N22: Target | X22: Check it's open before visiting: weak online evidence. | Y22: https://www.thehaifaroom.com
A23: 22 | B23: 1 | C23: The Lunch Lady of Saigon | D23: Ossington | E23: Restaurant | F23: Vietnamese | G23: 93 Ossington Ave | H23: https://thelunchlady.com | J23: 647-748-9550 | K23: $$ | L23: New Bib Gourmand with lunch and dinner service. | M23: Not checked | N23: Target | Y23: https://guide.michelin.com/ca/en/ontario/toronto/restaurant/the-lunch-lady-of-saigon
A24: 23 | B24: 1 | C24: Union | D24: Ossington | E24: Restaurant | F24: French bistro, seasonal | G24: 72 Ossington Ave | H24: https://union72.ca | I24: @union_restaurant | J24: 416-850-0093 | K24: $$$ | L24: Long-running seasonal bistro, a natural fit for a second-main offer. | M24: Not checked | N24: Target | Y24: https://guide.michelin.com/ca/en/ontario/toronto/restaurant/union-1198909
A25: 24 | B25: 1 | C25: The Lakeview | D25: Ossington | E25: Brunch | F25: Diner | G25: 1132 Dundas St W | H25: http://www.thelakeviewrestaurant.ca | I25: @thelakeviewdiner | J25: 416-850-8886 | L25: Classic diner at Ossington and Dundas with all-day breakfast. | M25: Not checked | N25: Target | X25: Check it's open before visiting: weak online evidence. | Y25: http://www.thelakeviewrestaurant.ca
A26: 25 | B26: 1 | C26: I Deal Coffee & Wine | D26: Ossington | E26: Café | F26: Coffee, pastries | G26: 162 Ossington Ave | L26: Early-opening café with a patio, good for weekday mornings. | M26: Not checked | N26: Target | Y26: https://www.designlinesmagazine.com/ossington-strip-neighbourhood-guide/
A27: 26 | B27: 1 | C27: Linny's Luncheonette | D27: Ossington | E27: Café | F27: Deli sandwiches | G27: 174 Ossington Ave | I27: @linnysluncheonette | L27: Daytime deli counter, suits a lunch offer. | M27: Not checked | N27: Target | Y27: https://streetsoftoronto.com/food/restaurants/the-6-best-new-restaurants-on-ossington/
A28: 27 | B28: 1 | C28: Manita | D28: Ossington | E28: Café | F28: All-day café, Mediterranean small plates | G28: 210 Ossington Ave | H28: https://www.manita.ca | I28: @manita.toronto | J28: 416-551-2230 | L28: All-day café that works for brunch and quiet weekday dinners. | M28: Not checked | N28: Target | X28: Check it's open before visiting: weak online evidence. | Y28: https://www.manita.ca
A29: 28 | B29: 1 | C29: Misc Coffee | D29: Ossington | E29: Café | F29: Coffee | G29: 299 Ossington Ave | L29: New café at the north end of the strip. | M29: Not checked | N29: Target | Y29: https://foodism.ca/eat-drink/bars-restaurants/best-new-restaurants-toronto-fall-2025/
A30: 29 | B30: 1 | C30: Stefano's Diner | D30: Ossington | E30: Café | F30: Vegan Italian sandwiches | G30: 1265 Dundas St W | H30: https://stefanosdiner.com | I30: @stefanosdiner | J30: 437-318-8697 | L30: Casual plant-based diner, sister to Gia. | M30: Not checked | N30: Target | Y30: https://streetsoftoronto.com/food/5-restaurants-on-dundas-west-that-every-foodie-needs-to-try/
A31: 30 | B31: 1 | C31: Formula Fig (Ossington) | D31: Ossington | E31: Spa | F31: Facial studio | G31: 50 Ossington Ave | H31: https://formulafig.com/ | I31: @formulafig | L31: Free targeted add-on with a signature facial. | M31: Not checked | N31: Target | Y31: https://curiocity.com/toronto-spas-massages-facials/
A32: 31 | B32: 1 | C32: Academy of Lions | D32: Ossington | E32: Studio | F32: Functional fitness | G32: 1083 Dundas St W | H32: https://www.academyoflions.com/ | I32: @academyoflions | L32: Bring a friend to a group class free. | M32: Not checked | N32: Target | Y32: https://www.academyoflions.com/
A33: 32 | B33: 1 | C33: Assembly Movement | D33: Ossington | E33: Studio | F33: Reformer pilates | G33: 832 College St; 1114 Queen St E | H33: https://www.assemblymovement.ca/ | I33: @assembly_movement | L33: Bring a friend to a reformer class free. | M33: Not checked | N33: Target | Y33: https://www.assemblymovement.ca/
A34: 33 | B34: 1 | C34: Downward Dog Yoga | D34: Ossington | E34: Studio | F34: Yoga (vinyasa, strength, pilates) | G34: 30 Ossington Ave, 2nd floor | H34: https://downwarddog.com/ | I34: @downwarddogyoga | L34: Bring a friend to class free. | M34: Not checked | N34: Target | Y34: https://ma.to/venue/downwarddogyoga
A35: 34 | B35: 1 | C35: MuseMovement | D35: Ossington | E35: Studio | F35: Pilates, barre and yoga | G35: 180 Shaw St, #204 | H35: https://www.musemovement.ca/ | I35: @muse_movement | L35: Bring a friend to a mat or barre class free. | M35: Not checked | N35: Target | Y35: https://www.musemovement.ca/
A36: 35 | B36: 1 | C36: Octopus Garden Yoga | D36: Ossington | E36: Studio | F36: Yoga and holistic centre | G36: 967 College St | H36: https://octopusgardenyoga.com/ | L36: Bring a friend to a drop-in class free. | M36: Not checked | N36: Target | X36: Check it's open before visiting: weak online evidence. | Y36: https://www.blogto.com/fitness/octopus-garden-yoga-toronto/
A37: 36 | B37: 1 | C37: Ride Cycle Club Ossington | D37: Ossington | E37: Studio | F37: Indoor cycling | G37: 19 Ossington Ave | H37: https://ridecycleclub.com/ | I37: @ridecycleclub | L37: Bring a friend to a ride free. | M37: Not checked | N37: Target | Y37: https://ridecycleclub.com/
A38: 37 | B38: 1 | C38: YogaSpace | D38: Ossington | E38: Studio | F38: Yoga | G38: 699 College St | H38: https://www.yogaspace.net/ | I38: @yogaspaceto | J38: 416-530-1622 | L38: Bring a friend to class free. | M38: Not checked | N38: Target | Y38: https://www.yogaspace.net/contact
A39: 38 | B39: 1 | C39: 156 OneFiveSix | D39: Queen West | E39: Restaurant | F39: Korean with French technique | G39: 1100 Queen St W | H39: https://156onefivesix.com | I39: @onefivesix_156 | J39: 416-469-4150 | K39: $$$ | L39: Michelin-listed Korean dinner spot, open Tuesday to Sunday. | M39: Not checked | N39: Target | Y39: https://guide.michelin.com/ca/en/ontario/toronto/restaurant/156-onefivesix
A40: 39 | B40: 1 | C40: Aleria | D40: Queen West | E40: Restaurant | F40: Greek | G40: 1070 Queen St W | H40: https://www.aleria.ca | I40: @aleria1070 | J40: 416-519-1109 | L40: Greek dining room with space for private dining. | M40: Not checked | N40: Target | X40: Check it's open before visiting: weak online evidence. | Y40: https://www.aleria.ca
A41: 40 | B41: 1 | C41: Aloette | D41: Queen West | E41: Restaurant | F41: Contemporary bistro | G41: 163 Spadina Ave | H41: https://aloetterestaurant.com | I41: @aloetterestaurants | J41: 416-260-3444 | K41: $$$ | L41: Bistro at Queen and Spadina, the east edge of the area. | M41: Not checked | N41: Target | Y41: https://guide.michelin.com/ca/en/ontario/toronto/restaurant/aloette
A42: 41 | B42: 1 | C42: Bar Prima | D42: Queen West | E42: Restaurant | F42: Italian | G42: 1136 Queen St W | H42: https://barprima.ca | I42: @barprima.to | J42: 647-347-9697 | L42: Italian spot at the west end of the strip. | M42: Not checked | N42: Target | X42: Check it's open before visiting: weak online evidence. | Y42: https://barprima.ca
A43: 42 | B43: 1 | C43: Bar Vendetta | D43: Queen West | E43: Restaurant | F43: Italian | G43: 928 Dundas St W | H43: https://www.barvendetta.com | I43: @barvendetta | J43: 416-551-8854 | K43: $$ | L43: Michelin-listed pasta spot that keeps seats for walk-ins. | M43: Not checked | N43: Target | Y43: https://guide.michelin.com/ca/en/ontario/toronto/restaurant/bar-vendetta
A44: 43 | B44: 1 | C44: Cassette (Gladstone House) | D44: Queen West | E44: Restaurant | F44: Comfort food, brunch | G44: 1214 Queen St W | H44: https://www.gladstonehouse.ca/eat-drink/ | I44: @gladstonehouseto | L44: Newer hotel restaurant for weekend brunch and dinner. | M44: Not checked | N44: Target | Y44: https://tdotevent.ca/blog/queen-west-ossington-bars-restaurants-2026.html
A45: 44 | B45: 1 | C45: Chez Nad | D45: Queen West | E45: Restaurant | F45: French bistro | G45: 780 Queen St W | H45: https://www.cheznad.com | I45: @cheznadtoronto | J45: 647-265-8864 | L45: New Lyonnais bistro behind Nadège, still building weeknights. | M45: Not checked | N45: Target | Y45: https://retail-insider.com/retail-insider/2026/01/nadege-nourian-launches-chez-nad-in-toronto/
A46: 45 | B46: 1 | C46: Fonda Lola | D46: Queen West | E46: Restaurant | F46: Mexican | G46: 942 Queen St W | J46: 647-706-9105 | L46: Neighbourhood Mexican near Shaw, known for tacos and ceviche. | M46: Not checked | N46: Target | Y46: https://opentable.ca/r/fonda-lola
A47: 46 | B47: 1 | C47: Gladstone Bistro (Gladstone House) | D47: Queen West | E47: Restaurant | F47: All-day bistro | G47: 1214 Queen St W | H47: https://www.gladstonehouse.ca/eat-drink/ | I47: @gladstonehouseto | J47: 416-531-4635 | L47: All-day hotel bistro with weekend brunch. | M47: Not checked | N47: Target | Y47: https://www.gladstonehouse.ca/eat-drink/
A48: 47 | B48: 1 | C48: Henry's | D48: Queen West | E48: Restaurant | F48: Contemporary, wine-focused | G48: 922 Queen St W | H48: https://www.henrystoronto.ca | I48: @henrys.to | J48: 416-386-5352 | K48: $$$ | L48: Wine-led neighbourhood room with weekend brunch. | M48: Not checked | N48: Target | Y48: https://guide.michelin.com/ca/en/ontario/toronto/restaurant/henry-s-1203157
A49: 48 | B49: 1 | C49: Jamil's Chaat House | D49: Queen West | E49: Restaurant | F49: Pakistani | G49: 1086 Queen St W | L49: Desi street-food dishes served sit-down. | M49: Not checked | N49: Target | Y49: https://streetsoftoronto.com/food/meet-the-pakistani-restaurant-thats-making-queen-west-cool-again/
A50: 49 | B50: 1 | C50: La Palma | D50: Queen West | E50: Restaurant | F50: California-Italian | G50: 849 Dundas St W | H50: https://lapalma.ca | I50: @lapalmato | J50: 416-368-4567 | L50: Shareable Italian plates near Trinity Bellwoods. | M50: Not checked | N50: Target | Y50: https://lapalma.ca
A51: 50 | B51: 1 | C51: Liliana | D51: Queen West | E51: Restaurant | F51: Italian with Asian influences | G51: 1198 Queen St W | H51: https://www.lilianatoronto.com | I51: @lilianarestaurant | J51: 416-539-0101 | K51: $$$$ | L51: Intimate 30-seat room, newly Michelin recommended. | M51: Not checked | N51: Target | Y51: https://guide.michelin.com/ca/en/ontario/toronto/restaurant/liliana
A52: 51 | B52: 1 | C52: Little Ese | D52: Queen West | E52: Restaurant | F52: Pizza, pasta | G52: 875 Queen St W | H52: https://littleese.com | I52: @eatlittleese | L52: Casual pizza spot across from Trinity Bellwoods with a big patio. | M52: Not checked | N52: Target | X52: Check it's open before visiting: weak online evidence. | Y52: https://www.blogto.com/eat_drink/2025/08/little-ese-plush-cafe-bar-toronto
A53: 52 | B53: 1 | C53: Loeithai Kitchen and Bar | D53: Queen West | E53: Restaurant | F53: Thai | G53: 640 Queen St W | H53: https://loeithai.ca | J53: 416-703-0279 | L53: Newer Thai room on the east end of the strip. | M53: Not checked | N53: Target | Y53: https://streetsoftoronto.com/toronto-shopping/best-new-openings-queen-west/
A54: 53 | B54: 1 | C54: Oyster Boy | D54: Queen West | E54: Restaurant | F54: Seafood, oysters | G54: 872 Queen St W | H54: https://oysterboy.ca | I54: @oysterboytoronto | J54: 416-534-3432 | L54: Seafood room open for dinner every night. | M54: Not checked | N54: Target | Y54: https://oysterboy.ca
A55: 54 | B55: 1 | C55: Prime Seafood Palace | D55: Queen West | E55: Restaurant | F55: Steakhouse | G55: 944 Queen St W | H55: https://primeseafoodpalace.ca | J55: 416-551-8038 | K55: $$$$ | L55: High-end steak house, a premium anchor for the list. | M55: Not checked | N55: Target | Y55: https://guide.michelin.com/ca/en/ontario/toronto/restaurant/prime-seafood-palace
A56: 55 | B56: 1 | C56: Terroni Queen | D56: Queen West | E56: Restaurant | F56: Southern Italian | G56: 720 Queen St W | H56: https://www.terroni.com/locations/terroni-queen | I56: @terroni.to | J56: 416-504-0320 | L56: Original 1992 Terroni with a back patio and weekend brunch. | M56: Not checked | N56: Target | Y56: https://www.terroni.com/locations/terroni-queen
A57: 56 | B57: 1 | C57: The Drake Hotel | D57: Queen West | E57: Restaurant | F57: Hotel restaurant | G57: 1150 Queen St W | H57: https://thedrake.ca | I57: @thedrakehotel | J57: 416-531-5042 | L57: Boutique hotel dining room, fits a hotel restaurant offer. | M57: Not checked | N57: Target | Y57: https://thedrake.ca
A58: 57 | B58: 1 | C58: The Good Son | D58: Queen West | E58: Restaurant | F58: Wood-fired pizza, comfort food | G58: 1096 Queen St W | H58: https://thegoodsontoronto.com | I58: @thegoodson_to | J58: 437-447-5934 | L58: Wood-fired pizza and comfort food, an easy weeknight pick. | M58: Not checked | N58: Target | X58: Check it's open before visiting: weak online evidence. | Y58: https://thegoodsontoronto.com
A59: 58 | B59: 1 | C59: The Hive by Honey Soul Food | D59: Queen West | E59: Restaurant | F59: Soul food, halal-friendly | G59: 907 Dundas St W | L59: Halal-friendly soul food in the old Saving Grace space. | M59: Not checked | N59: Target | Y59: https://foodism.ca/eat-drink/bars-restaurants/best-new-restaurants-toronto-fall-2025/
A60: 59 | B60: 1 | C60: Sisters & Co | D60: Queen West | E60: Brunch | F60: Asian-inspired brunch | G60: 887 Dundas St W | L60: Friendly brunch spot on the north side of Trinity Bellwoods. | M60: Not checked | N60: Target | Y60: https://www.ctvnews.ca/toronto/article/this-toronto-restaurant-serves-up-pancakes-endorsed-by-bad-bunny/
A61: 60 | B61: 1 | C61: Plush Cafe & Bar | D61: Queen West | E61: Café | F61: Global comfort food, brunch | G61: 897 Queen St W | H61: https://plushcafe.ca | I61: @plushcafeto | J61: 647-368-6687 | L61: Café by day with brunch and dinner, right across from the park. | M61: Not checked | N61: Target | Y61: https://www.blogto.com/eat_drink/2026/04/new-cafes-toronto-april-2026/
A62: 61 | B62: 1 | C62: Trinity Market | D62: Queen West | E62: Café | F62: Café and snack bar | G62: 768A Queen St W | H62: https://trinitymarket.ca | I62: @trinitymarketto | J62: 647-358-3663 | L62: Café and snack bar near the park, good for daytime offers. | M62: Not checked | N62: Target | X62: Check it's open before visiting: weak online evidence. | Y62: https://trinitymarket.ca
A63: 62 | B63: 1 | C63: Nadège Patisserie | D63: Queen West | E63: Bakery | F63: French pastry | G63: 780 Queen St W | L63: Flagship French pastry shop across from the park. | M63: Not checked | N63: Target | Y63: https://retail-insider.com/retail-insider/2026/01/nadege-nourian-launches-chez-nad-in-toronto/
A64: 63 | B64: 1 | C64: Sud Forno Queen | D64: Queen West | E64: Bakery | F64: Italian bakery and café | G64: 716 Queen St W | H64: https://www.terroni.com/locations/sud-forno-queen | L64: Bakery café next to Terroni, suits a coffee and pastry offer. | M64: Not checked | N64: Target | Y64: https://www.terroni.com/locations/sud-forno-queen
A65: 64 | B65: 1 | C65: Imprint Pilates | D65: Queen West | E65: Studio | F65: Pilates (private and semi-private) | G65: 204 Spadina Ave | H65: https://www.imprintpilates.com/ | I65: @imprintpilates | L65: Bring a friend to a semi-private session free. | M65: Not checked | N65: Target | Y65: https://www.imprintpilates.com/
A66: 65 | B66: 1 | C66: Jaybird (Queen West) | D66: Queen West | E66: Studio | F66: Pilates (mat and reformer) | G66: 735 Queen St W | H66: https://www.jaybirdjaybird.com/ | L66: Bring a friend to a mat class free. | M66: Not checked | N66: Target | Y66: https://curiocity.com/toronto-wellness-studios-ontario/
A67: 66 | B67: 1 | C67: Yoga Tree (Spadina) | D67: Queen West | E67: Studio | F67: Yoga and hot yoga | G67: 140 Spadina Ave | H67: https://www.yogatree.ca/ | I67: @yogatreestudios | L67: Bring a friend to class free. | M67: Not checked | N67: Target | Y67: https://www.yogatree.ca/locations
A68: 67 | B68: 1 | C68: Gladstone House | D68: Queen West | E68: Hotel restaurant or spa | F68: Hotel restaurant | G68: 1214 Queen St W | H68: https://www.gladstonehouse.ca/ | I68: @gladstonehouseto | L68: Second brunch main on us, weekdays. | M68: Not checked | N68: Target | Y68: https://www.gladstonehouse.ca/
A69: 68 | B69: 1 | C69: Aera | D69: King West | E69: Restaurant | F69: Steakhouse and sushi | G69: 8 Spadina Ave, 38th floor (The Well) | H69: https://aerarestaurant.com/ | I69: @aera.restaurant | J69: 647-258-5207 | L69: High-floor dining with views, good for special occasions. | M69: Not checked | N69: Target | Y69: https://aerarestaurant.com/
A70: 69 | B70: 1 | C70: Animl Steakhouse | D70: King West | E70: Restaurant | F70: Steakhouse | G70: 420A Wellington St W | H70: https://animlsteakhouse.com/ | J70: 416-764-6094 | L70: Premium steakhouse that may want early-week covers. | M70: Not checked | N70: Target | Y70: https://animlsteakhouse.com/
A71: 70 | B71: 1 | C71: Baro | D71: King West | E71: Restaurant | F71: Latin American | G71: 485 King St W | H71: https://barotoronto.com/ | I71: @barotoronto | J71: 416-363-8388 | L71: Large Latin room, quieter on Monday to Wednesday nights. | M71: Not checked | N71: Target | Y71: https://barotoronto.com/
A72: 71 | B72: 1 | C72: Bridgette Bar | D72: King West | E72: Restaurant | F72: Mediterranean | G72: 423 Wellington St W | H72: https://www.bridgettebar.com/ | I72: @thebridgettebar | J72: 647-258-5203 | L72: Chef-driven room at The Well with a lunch crowd from nearby offices. | M72: Not checked | N72: Target | Y72: https://www.opentable.com.au/r/bridgette-bar-toronto
A73: 72 | B73: 1 | C73: Buca | D73: King West | E73: Restaurant | F73: Italian | G73: 604 King St W | H73: https://buca.ca/ | I73: @bucatoronto | J73: 416-865-1600 | L73: Premium Italian, ideal flagship partner for a curated list. | M73: Not checked | N73: Target | Y73: https://buca.ca/
A74: 73 | B74: 1 | C74: Campechano | D74: King West | E74: Restaurant | F74: Mexican | G74: 504 Adelaide St W | H74: https://campechano.ca/ | J74: 416-777-2800 | L74: Casual taqueria for a weeknight bite with a friend. | M74: Not checked | N74: Target | Y74: https://campechano.ca/
A75: 74 | B75: 1 | C75: Cassius | D75: King West | E75: Restaurant | F75: Italian | G75: 624 King St W | H75: https://www.cassiusonking.com/ | I75: @cassiusonking | J75: 416-777-9779 | L75: New Italian room on King West, good for date nights early in the week. | M75: Not checked | N75: Target | Y75: https://www.cassiusonking.com/
A76: 75 | B76: 1 | C76: Chubby's Jamaican Kitchen | D76: King West | E76: Restaurant | F76: Caribbean | G76: 104 Portland St | H76: https://chubbysjamaican.com/ | I76: @chubbysjamaican | J76: 416-792-8105 | K76: $$$ | L76: Lively Jamaican spot with brunch, popular with groups. | M76: Not checked | N76: Target | Y76: https://www.opentable.ca/r/chubbys-jamaican-kitchen-toronto
A77: 76 | B77: 1 | C77: Edulis | D77: King West | E77: Restaurant | F77: Seasonal | G77: 169 Niagara St | H77: https://www.edulisrestaurant.com/ | J77: 416-703-4222 | L77: Small chef-owned room; a hand-picked partner with real credibility. | M77: Not checked | N77: Target | X77: Check it's open before visiting: weak online evidence. | Y77: https://www.edulisrestaurant.com/
A78: 77 | B78: 1 | C78: Gusto 101 | D78: King West | E78: Restaurant | F78: Italian | G78: 101 Portland St | H78: https://www.gusto101.com/ | J78: 416-504-9669 | L78: Busy Italian with a rooftop patio, well known to the target crowd. | M78: Not checked | N78: Target | X78: Check it's open before visiting: weak online evidence. | Y78: https://www.opentable.ca/gusto-101-reservations-toronto
A79: 78 | B79: 1 | C79: Honey Chinese | D79: King West | E79: Restaurant | F79: Chinese | G79: 600 King St W, 3rd floor (Portland Square) | H79: https://honeychineseto.com/ | I79: @honeychineseto | J79: 437-222-6142 | L79: Upscale Chinese in Portland Square, a fit for group and date dinners. | M79: Not checked | N79: Target | Y79: https://penthousequeen.com/blog/the-corner-where-king-west-is-arguing-with-itself
A80: 79 | B80: 1 | C80: La Plume Brasserie | D80: King West | E80: Restaurant | F80: French | G80: 453 Wellington St W | H80: https://www.laplumebrasserie.com/ | I80: @laplumebrasserie | J80: 647-258-5205 | L80: French brasserie with weekend brunch, near The Well offices. | M80: Not checked | N80: Target | Y80: https://www.laplumebrasserie.com/
A81: 80 | B81: 1 | C81: Laissez Faire | D81: King West | E81: Restaurant | F81: French-Mediterranean | G81: 589 King St W | H81: https://laissezfairetoronto.com/ | I81: @laissezfairetoronto | J81: 647-508-5088 | K81: $$ | L81: Weekend brunch and dinner at King and Portland, approachable prices. | M81: Not checked | N81: Target | Y81: https://www.opentable.ca/r/laissez-faire-toronto
A82: 81 | B82: 1 | C82: Le Select Bistro | D82: King West | E82: Restaurant | F82: French | G82: 432 Wellington St W | J82: 416-596-6405 | L82: Long-running French bistro with brunch; a staple for date nights. | M82: Not checked | N82: Target | X82: Check it's open before visiting: weak online evidence. | Y82: https://www.opentable.ca/r/le-select-bistro-toronto
A83: 82 | B83: 1 | C83: Little Baba | D83: King West | E83: Restaurant | F83: Middle Eastern | G83: 75 Portland St | H83: https://littlebaba.com/ | I83: @littlebaba.to | J83: 647-265-8237 | L83: Shareable Middle Eastern plates suit a bring-a-friend offer. | M83: Not checked | N83: Target | Y83: https://littlebaba.com/
A84: 83 | B84: 1 | C84: Mademoiselle Raw Bar + Grill | D84: King West | E84: Restaurant | F84: Seafood | G84: 563 King St W | H84: http://mademoiselleto.com/ | I84: @mademoiselleto | J84: 416-598-2003 | L84: Seafood and grill for special dinners, room to fill early in the week. | M84: Not checked | N84: Target | Y84: http://mademoiselleto.com/
A85: 84 | B85: 1 | C85: Miss Likklemore's | D85: King West | E85: Restaurant | F85: Caribbean | G85: 433 King St W | H85: https://misslikklemores.com/ | J85: 647-484-8789 | L85: Upscale Caribbean with a family-style menu that suits sharing. | M85: Not checked | N85: Target | Y85: https://streetsoftoronto.com/restaurant/miss-likklemores/
A86: 85 | B86: 1 | C86: Myth | D86: King West | E86: Restaurant | F86: Greek | G86: 522 King St W | H86: https://mythrestaurant.com/ | J86: 416-703-2800 | K86: $$$$ | L86: Mykonos-style Greek room, quieter early in the week. | M86: Not checked | N86: Target | Y86: https://www.opentable.ca/restaurant/profile/1184893
A87: 86 | B87: 1 | C87: Noyaa | D87: King West | E87: Restaurant | F87: Mediterranean-Asian | G87: 486 Front St W (The Well) | H87: https://www.noyaatoronto.com/ | I87: @noyaatoronto | J87: 647-243-2707 | L87: Mediterranean-Asian at The Well, near the office crowd. | M87: Not checked | N87: Target | Y87: https://www.noyaatoronto.com/
A88: 87 | B88: 1 | C88: Oretta | D88: King West | E88: Restaurant | F88: Italian | G88: 633 King St W | H88: https://www.oretta.to/ | I88: @orettatoronto | J88: 416-944-1932 | L88: Italian dining room with a strong brunch following. | M88: Not checked | N88: Target | Y88: https://www.oretta.to/
A89: 88 | B89: 1 | C89: Primadonna | D89: King West | E89: Restaurant | F89: Italian | G89: 600 King St W, rooftop (Portland Square) | H89: https://primadonnatoronto.com/ | I89: @primadonnato | J89: 437-222-6140 | L89: Rooftop Italian that could use quieter weeknight covers. | M89: Not checked | N89: Target | Y89: https://penthousequeen.com/blog/the-corner-where-king-west-is-arguing-with-itself
A90: 89 | B90: 1 | C90: Public Gardens | D90: King West | E90: Restaurant | F90: Italian-American | G90: 577 King St W | H90: https://www.public-gardens.com/ | I90: @publicgardenstoronto | L90: Italian-American plates for friends; evenings Monday to Thursday likely have room. | M90: Not checked | N90: Target | Y90: https://www.public-gardens.com/
A91: 90 | B91: 1 | C91: Rodney's Oyster House | D91: King West | E91: Restaurant | F91: Seafood | G91: 469 King St W | H91: https://rodneysoysterhouse.com/ | I91: @rodneysoysterhouse | J91: 416-363-8105 | L91: Classic seafood room, popular for business dinners. | M91: Not checked | N91: Target | Y91: https://rodneysoysterhouse.com/
A92: 91 | B92: 1 | C92: SARA (The Journey) | D92: King West | E92: Restaurant | F92: Tasting menu | G92: 98 Portland St | H92: https://www.sara.restaurant/ | I92: @sararestaurantto | J92: 416-985-5721 | L92: Special-occasion tasting menu; a free upgrade offer may fit better than two-for-one. | M92: Not checked | N92: Target | Y92: https://penthousequeen.com/blog/the-corner-where-king-west-is-arguing-with-itself
A93: 92 | B93: 1 | C93: The Dorset | D93: King West | E93: Restaurant | F93: British | G93: 457 Wellington St W | H93: https://www.thedorsetwellington.com/ | I93: @thedorset.to | J93: 647-288-4304 | L93: British coastal menu at The Well, near office towers for lunch. | M93: Not checked | N93: Target | Y93: https://www.thedorsetwellington.com/
A94: 93 | B94: 1 | C94: Vinny | D94: King West | E94: Restaurant | F94: Eclectic | G94: 478 King St W | H94: https://vinnytoronto.com/ | I94: @vinny.toronto | J94: 647-660-0999 | L94: Restaurant with a vinyl bar, appeals to the young professional crowd. | M94: Not checked | N94: Target | Y94: https://www.blogto.com/eat_drink/2025/07/vinny-vinyl-bar-toronto
A95: 94 | B95: 1 | C95: L'Avenue Toronto | D95: King West | E95: Brunch | F95: Brunch | G95: 433 Wellington St W | H95: https://restolavenue.ca/ | I95: @lavenueresto | J95: 416-722-8678 | L95: Brunch spot at The Well, good for weekday brunch traffic. | M95: Not checked | N95: Target | Y95: https://restolavenue.ca/accueil
A96: 95 | B96: 1 | C96: Dark Horse Coffee | D96: King West | E96: Café | F96: Coffee | G96: 88 Bathurst St (West House) | L96: Local coffee café on the west edge of King West. | M96: Not checked | N96: Target | Y96: https://penthousequeen.com/blog/the-corner-where-king-west-is-arguing-with-itself
A97: 96 | B97: 1 | C97: De Mello at The Well | D97: King West | E97: Café | F97: Coffee | G97: 8 Spadina Ave (The Well office lobby) | H97: https://hellodemello.com/ | I97: @demellocoffee | J97: 416-556-5393 | L97: Busy office-lobby café, a daily habit for The Well workers. | M97: Not checked | N97: Target | Y97: https://thewelltoronto.com/directory/de-mello-coffee
A98: 97 | B98: 1 | C98: Nonni Cafe & Bakery | D98: King West | E98: Café | F98: Italian café | G98: 430 King St W | H98: https://nonnicafe.ca/ | I98: @nonni.to | J98: 416-622-8069 | L98: All-day café with seating, good for breakfast and lunch offers. | M98: Not checked | N98: Target | Y98: https://nonnicafe.ca/
A99: 98 | B99: 1 | C99: AIRE Ancient Baths Toronto | D99: King West | E99: Spa | F99: Thermal bathhouse | G99: 510A Front St W | L99: Free massage upgrade with a bath experience, off-peak days. | M99: Not checked | N99: Target | Y99: https://curiocity.com/aire-ancient-baths-toronto-now-open/
A100: 99 | B100: 1 | C100: Hammam Spa by Céla | D100: King West | E100: Spa | F100: Hammam and day spa | G100: 602 King St W | H100: https://hammamspa.ca/ | I100: @hammamspa | L100: Free add-on such as a scrub upgrade with a hammam ritual. | M100: Not checked | N100: Target | Y100: https://curiocity.com/best-spas-toronto-city-escape/
...

Sheet Lists
A1: Status | B1: Neighbourhood | C1: Category | D1: How we know them | E1: Open?
A2: Target | B2: Ossington | C2: Restaurant | D2: Walked in | E2: Not checked
A3: Contacted | B3: Queen West | C3: Brunch | D3: Email | E3: Confirmed open
A4: Meeting booked | B4: King West | C4: Café | D4: Instagram | E4: Closed
A5: Met | B5: Financial District | C5: Bakery | D5: Friend
A6: LOI signed | B6: Yorkville | C6: Spa | D6: Referral
A7: Agreement signed | B7: Leslieville | C7: Studio | D7: Event
A8: Not now | B8: Little Italy | C8: Hotel restaurant or spa
B9: Kensington and Chinatown | C9: Experience
B10: The Annex
B11: Roncesvalles
B12: Danforth
B13: Liberty Village
B14: Little Portugal
B15: Parkdale
B16: The Junction
B17: St. Clair West
B18: Distillery and Corktown
B19: Summerhill and Rosedale
B20: Midtown
B21: Leaside
B22: Riverdale
